[{"id":1,"name":"Отчетность через интернет","link":"/otchetnost/","non_changes_link":"https://taxcom.ru/otchetnost/","img":"https://taxcom.ru/products/img/icon_otch.svg","img_path":"/images/icon_otch.svg","services":[{"id":1,"name":"Нулевой","subtitle":"Для сдачи нулевой отчётности для ИП","price":"1100","link":"https://order.taxcom.ru/multiorder?RegType=EDO_Nulevoj_IP","description":[{"name":"Онлайн-спринтер","services":"Программа/сервис ","show":true},{"name":"ФНС, ПФР, ФСС","services":"Безлимитная отчетность во все подразделения ","show":true},{"name":"В тарифе + бесплатная замена","services":"Электронная подпись (ЭП) ","show":true},{"name":"Лицензия КриптоПро CSP на 1 год","services":"Программа для работы с ЭП ","show":true},{"name":"Все формы для нулевых отчетов","services":"Готовые формы ","show":true},{"name":"","services":"Подходит для ИП, которые не вели хозяйственную деятельность за отчетный период ","show":true}],"additional_payment":["СМС-уведомления ","Выезд, настройка и обучение"],"advantages":["Безлимитная замена электронной подписи","Все формы для нулевых отчетов","Проверка на ошибки","Умный календарь бухгалтера","Обучение и семинары с экспертами ФНС","Мобильный Такском-Информер","Сверка с бюджетом","Техподдержка 24/7","Готовые формы"],"classForView":"tariff","view":false},{"id":2,"name":"Нулевой","subtitle":"Для сдачи нулевой отчётности для ЮЛ","price":"1600","link":"https://order.taxcom.ru/multiorder?RegType=EDO_Nulevoj","description":[{"name":"Онлайн-спринтер","services":"Программа/сервис ","show":true},{"name":"ФНС, ПФР, ФСС","services":"Безлимитная отчетность во все подразделения ","show":true},{"name":"В тарифе + бесплатная замена","services":"Электронная подпись (ЭП) ","show":true},{"name":"Лицензия КриптоПро CSP на 1 год","services":"Программа для работы с ЭП ","show":true},{"name":"Все формы для нулевых отчетов","services":"Готовые формы ","show":true},{"name":"","services":"Подходит для ЮЛ, которые не вели хозяйственную деятельность за отчетный период ","show":true}],"additional_payment":["СМС-уведомления ","Выезд, настройка и обучение"],"advantages":["Безлимитная замена электронной подписи","Все формы для нулевых отчетов","Проверка на ошибки","Умный календарь бухгалтера","Обучение и семинары с экспертами ФНС","Мобильный Такском-Информер","Сверка с бюджетом","Техподдержка 24/7","Готовые формы"],"classForView":"tariff","view":false},{"id":3,"name":"Привычный-1С. ИП","subtitle":"индивидуальным предпринимателям","price":"1800","link":"https://order.taxcom.ru/multiorder?RegType=EDO_1cPrivichnyiIP","description":[{"name":"1С:Отчётность","services":"Программа/сервис ","show":true},{"name":"ФНС, ПФР, ФСС, Росстат, ФСРАР и ФТС","services":"Безлимитная отчетность во все подразделения ","show":true},{"name":"100 исходящих документов","services":"Электронный документооборот с партнёрами ","show":true},{"name":"5 лицензий Базовая С","services":"Проверка контрагентов ","show":true},{"name":"Мобильное приложение Такском-Информер","services":"Получение уведомлений от госорганов ","show":true}],"classForView":"tariff","view":false},{"id":4,"name":"Привычный-1С","subtitle":"юридическим лицам","price":"4900","link":"https://order.taxcom.ru/multiorder?RegType=EDO_1cPrivichnyi","description":[{"name":"1С:Отчётность","services":"Программа/сервис ","show":true},{"name":"ФНС, ПФР, ФСС, Росстат, ФСРАР и ФТС","services":"Безлимитная отчетность во все подразделения ","show":true},{"name":"100 исходящих документов","services":"Электронный документооборот с партнёрами ","show":true},{"name":"5 лицензий Базовая С","services":"Проверка контрагентов ","show":true},{"name":"Мобильное приложение Такском-Информер","services":"Получение уведомлений от госорганов ","show":true}],"classForView":"tariff","view":false},{"id":5,"name":"Удобный","subtitle":"Минимальный старт","price":"2475","link":"https://order.taxcom.ru/multiorder?RegType=EDO_UdobniyIP2020","description":[{"name":"Онлайн-спринтер","services":"Программа/сервис ","show":true},{"name":"ФНС, ПФР","services":"Безлимитная отчетность во все подразделения ","show":true},{"name":"В тарифе + бесплатная замена","services":"Электронная подпись (ЭП) ","show":true},{"name":"Лицензия КриптоПро CSP на 1 год","services":"Программа для работы с ЭП ","show":true}],"additional_payment":["СМС-уведомления ","Выезд, настройка и обучение ","Отчетность в ФСС, Росстат, РПН, ЦБ РФ"],"advantages":["Безлимитная замена электронной подписи","Проверка на ошибки","Сверка с ФНС и ПФР","Умный календарь бухгалтера","Обучение и семинары с экспертами ФНС","Такском-Информер","Работа с электронными больничными","Отправка новой формы СЗВ-ТД","Сверка по НДС","Техподдержка 24/7"],"classForView":"stock stock25 tariff","view":false},{"id":6,"name":"Комфортный","subtitle":"Стандартное решение","price":"3975","link":"https://order.taxcom.ru/multiorder?RegType=EDO_ComfortniyIP2020","description":[{"name":"Онлайн-спринтер","services":"Программа/сервис ","show":true},{"name":"ФНС, ПФР, ФСС","services":"Безлимитная отчетность во все подразделения ","show":true},{"name":"В тарифе + бесплатная замена","services":"Электронная подпись (ЭП) ","show":true},{"name":"Лицензия КриптоПро CSP на 1 год","services":"Программа для работы с ЭП ","show":true},{"name":"600 исходящих документов","services":"Электронный документооборот с партнёрами ","show":true},{"name":"1 лицензия Базовая С","services":"Проверка контрагентов ","show":true}],"additional_payment":["СМС-уведомления ","Выезд, настройка и обучение ","Отчетность в Росстат, РПН, ЦБ РФ ","Дополнительное рабочее место для кадровика"],"advantages":["Безлимитная замена электронной подписи","Проверка на ошибки","Умный календарь бухгалтера","Обучение и семинары с экспертами ФНС","Такском-Информер","Работа с электронными больничными","Отправка новой формы СЗВ-ТД","Сверка по НДС","Актуальные формы отчетов","Техподдержка 24/7"],"classForView":"stock stock25 tariff","view":false},{"id":7,"name":"Солидный","subtitle":"Полноценная работа для всех","price":"6000","link":"https://order.taxcom.ru/multiorder?RegType=EDO_SolidniyIP2020","description":[{"name":"Онлайн-спринтер","services":"Программа/сервис ","show":true},{"name":"ФНС, ПФР, ФСС, Росстат, РПН","services":"Безлимитная отчетность во все подразделения ","show":true},{"name":"В тарифе + бесплатная замена","services":"Электронная подпись (ЭП) ","show":true},{"name":"Лицензия КриптоПро CSP на 1 год","services":"Программа для работы с ЭП ","show":true},{"name":"1 200 исходящих документов","services":"Электронный документооборот с партнёрами ","show":true},{"name":"5 лицензий Базовая С","services":"Проверка контрагентов ","show":true}],"additional_payment":["СМС-уведомления ","Выезд, настройка и обучение ","Дополнительное рабочее место для кадровика"],"advantages":["Безлимитная замена электронной подписи","Проверка на ошибки","Умный календарь бухгалтера","Обучение и семинары с экспертами ФНС","Такском-Информер","Работа с электронными больничными","Отправка новой формы СЗВ-ТД","Сверка по НДС","Актуальные формы отчетов","Техподдержка 24/7"],"classForView":"best stock stock25 tariff","view":false},{"id":8,"name":"Комфортный. Спецрежим","subtitle":"Стандартное решение","price":"3300","link":"https://order.taxcom.ru/multiorder?RegType=EDO_ComfortniySpecIP2020","description":[{"name":"Онлайн-спринтер","services":"Программа/сервис ","show":true},{"name":"ФНС, ПФР, ФСС","services":"Безлимитная отчетность во все подразделения ","show":true},{"name":"В тарифе + бесплатная замена","services":"Электронная подпись (ЭП) ","show":true},{"name":"Лицензия КриптоПро CSP на 1 год","services":"Программа для работы с ЭП ","show":true},{"name":"600 исходящих документов","services":"Электронный документооборот с партнёрами ","show":true},{"name":"1 лицензия Базовая С","services":"Проверка контрагентов ","show":true},{"name":"Актуальные формы отчетов","services":"Готовые формы ","show":true}],"additional_payment":["СМС-уведомления ","Выезд, настройка и обучение ","Отчетность в Росстат, РПН, ЦБ РФ ","Дополнительное рабочее место для кадровика"],"advantages":["Безлимитная замена электронной подписи","Проверка на ошибки","Умный календарь бухгалтера","Обучение и семинары с экспертами ФНС","Такском-Информер","Работа с электронными больничными","Отправка новой формы СЗВ-ТД","Сверка по НДС","Актуальные формы отчетов","Техподдержка 24/7"],"classForView":"stock stock25 tariff","view":false},{"id":9,"name":"Солидный. Спецрежим","subtitle":"Полноценная работа для всех","price":"4800","link":"https://order.taxcom.ru/multiorder?RegType=EDO_SolidniySpecIP2020","description":[{"name":"Онлайн-спринтер","services":"Программа/сервис ","show":true},{"name":"ФНС, ПФР, ФСС, Росстат, ЦБ РФ, РПН","services":"Безлимитная отчетность во все подразделения ","show":true},{"name":"В тарифе + бесплатная замена","services":"Электронная подпись (ЭП) ","show":true},{"name":"Лицензия КриптоПро CSP на 1 год","services":"Программа для работы с ЭП ","show":true},{"name":"1 200 исходящих документов","services":"Электронный документооборот с партнёрами ","show":true},{"name":"5 лицензий Базовая С","services":"Проверка контрагентов ","show":true},{"name":"Актуальные формы отчетов","services":"Готовые формы ","show":true}],"additional_payment":["СМС-уведомления ","Выезд, настройка и обучение ","Дополнительное рабочее место для кадровика"],"advantages":["Безлимитная замена электронной подписи","Проверка на ошибки","Умный календарь бухгалтера","Обучение и семинары с экспертами ФНС","Такском-Информер","Работа с электронными больничными","Отправка новой формы СЗВ-ТД","Сверка по НДС","Актуальные формы отчетов","Техподдержка 24/7"],"classForView":"best stock stock25 tariff","view":false},{"id":10,"name":"Удобный","subtitle":"Минимальный старт","price":"3675","link":"https://order.taxcom.ru/multiorder?RegType=EDO_Udobniy","description":[{"name":"Онлайн-спринтер","services":"Программа/сервис ","show":true},{"name":"ФНС, ПФР","services":"Безлимитная отчетность во все подразделения ","show":true},{"name":"В тарифе + бесплатная замена","services":"Электронная подпись (ЭП) ","show":true},{"name":"Лицензия КриптоПро CSP на 1 год","services":"Программа для работы с ЭП ","show":true}],"additional_payment":["СМС-уведомления ","Выезд, настройка и обучение ","Отчетность в ФСС, Росстат, РПН, ЦБ РФ"],"advantages":["Безлимитная замена электронной подписи","Проверка на ошибки","Сверка с ФНС и ПФР","Умный календарь бухгалтера","Обучение и семинары с экспертами ФНС","Такском-Информер","Работа с электронными больничными","Отправка новой формы СЗВ-ТД","Сверка по НДС","Техподдержка 24/7"],"classForView":"stock stock25 tariff","view":false},{"id":11,"name":"Комфортный","subtitle":"Стандартное решение","price":"4575","link":"https://order.taxcom.ru/multiorder?RegType=EDO_Comfortniy","description":[{"name":"Онлайн-спринтер","services":"Программа/сервис ","show":true},{"name":"ФНС, ПФР, ФСС + Росстат в подарок!","services":"Безлимитная отчетность во все подразделения ","show":true},{"name":"В тарифе + бесплатная замена","services":"Электронная подпись (ЭП) ","show":true},{"name":"Лицензия КриптоПро CSP на 1 год","services":"Программа для работы с ЭП ","show":true},{"name":"600 исходящих документов","services":"Электронный документооборот с партнёрами ","show":true},{"name":"1 лицензия Базовая С","services":"Проверка контрагентов ","show":true}],"additional_payment":["СМС-уведомления ","Выезд, настройка и обучение ","Отчетность в РПН, ЦБ РФ, Росстат ","Дополнительное рабочее место для кадровика"],"advantages":["Безлимитная замена электронной подписи","Проверка на ошибки","Умный календарь бухгалтера","Обучение и семинары с экспертами ФНС","Такском-Информер","Работа с электронными больничными","Отправка новой формы СЗВ-ТД","Сверка по НДС","Актуальные формы отчетов","Техподдержка 24/7"],"classForView":"stock stock25 tariff","view":false},{"id":12,"name":"Солидный","subtitle":"Полноценная работа для всех","price":"8175","link":"https://order.taxcom.ru/multiorder?RegType=EDO_Solidniy","description":[{"name":"Онлайн-спринтер","services":"Программа/сервис ","show":true},{"name":"ФНС, ПФР, ФСС, Росстат, ЦБ РФ, РПН","services":"Безлимитная отчетность во все подразделения ","show":true},{"name":"В тарифе + бесплатная замена","services":"Электронная подпись (ЭП) ","show":true},{"name":"Лицензия КриптоПро CSP на 1 год","services":"Программа для работы с ЭП ","show":true},{"name":"1 200 исходящих документов","services":"Электронный документооборот с партнёрами ","show":true},{"name":"5 лицензий Базовая С","services":"Проверка контрагентов ","show":true}],"additional_payment":["СМС-уведомления ","Выезд, настройка и обучение ","Дополнительное рабочее место для кадровика"],"advantages":["Безлимитная замена электронной подписи","Проверка на ошибки","Умный календарь бухгалтера","Обучение и семинары с экспертами ФНС","Такском-Информер","Работа с электронными больничными","Отправка новой формы СЗВ-ТД","Сверка по НДС","Актуальные формы отчетов","Техподдержка 24/7"],"classForView":"best stock stock25 tariff","view":false},{"id":13,"name":"Удобный. Спецрежим","subtitle":"Минимальный старт","price":"3300","link":"https://order.taxcom.ru/multiorder?RegType=EDO_UdobniySpecRejim2020","description":[{"name":"Онлайн-спринтер","services":"Программа/сервис ","show":true},{"name":"ФНС, ПФР","services":"Безлимитная отчетность во все подразделения ","show":true},{"name":"В тарифе + бесплатная замена","services":"Электронная подпись (ЭП) ","show":true},{"name":"Лицензия КриптоПро CSP на 1 год","services":"Программа для работы с ЭП ","show":true},{"name":"Актуальные формы отчетов","services":"Готовые формы ","show":true}],"additional_payment":["СМС-уведомления ","Выезд, настройка и обучение ","Отчетность в ФСС, Росстат, РПН, ЦБ РФ"],"advantages":["Проверка на ошибки","Сверка с ФНС и ПФР","Умный календарь бухгалтера","Обучение и семинары с экспертами ФНС","Такском-Информер","Работа с электронными больничными","Отправка новой формы СЗВ-ТД","Сверка по НДС","Техподдержка 24/7"],"classForView":"stock stock25 tariff","view":false},{"id":14,"name":"Комфортный. Спецрежим","subtitle":"Стандартное решение","price":"3675","link":"https://order.taxcom.ru/multiorder?RegType=EDO_ComfortniySpec","description":[{"name":"Онлайн-спринтер","services":"Программа/сервис ","show":true},{"name":"ФНС, ПФР, ФСС + Росстат в подарок!","services":"Безлимитная отчетность во все подразделения ","show":true},{"name":"В тарифе + бесплатная замена","services":"Электронная подпись (ЭП) ","show":true},{"name":"Лицензия КриптоПро CSP на 1 год","services":"Программа для работы с ЭП ","show":true},{"name":"600 исходящих документов","services":"Электронный документооборот с партнёрами ","show":true},{"name":"1 лицензия Базовая С","services":"Проверка контрагентов ","show":true},{"name":"Актуальные формы отчетов","services":"Готовые формы ","show":true}],"additional_payment":["СМС-уведомления ","Выезд, настройка и обучение ","Отчетность в РПН, ЦБ РФ, Росстат ","Дополнительное рабочее место для кадровика"],"advantages":["Безлимитная замена электронной подписи","Проверка на ошибки","Умный календарь бухгалтера","Обучение и семинары с экспертами ФНС","Такском-Информер","Работа с электронными больничными","Отправка новой формы СЗВ-ТД","Сверка по НДС","Актуальные формы отчетов","Техподдержка 24/7"],"classForView":"stock stock25 tariff","view":false},{"id":15,"name":"Солидный. Спецрежим","subtitle":"Полноценная работа для всех","price":"5775","link":"https://order.taxcom.ru/multiorder?RegType=EDO_SolidniySpec","description":[{"name":"Онлайн-спринтер","services":"Программа/сервис ","show":true},{"name":"ФНС, ПФР, ФСС, Росстат, ЦБ РФ, РПН","services":"Безлимитная отчетность во все подразделения ","show":true},{"name":"В тарифе + бесплатная замена","services":"Электронная подпись (ЭП) ","show":true},{"name":"Лицензия КриптоПро CSP на 1 год","services":"Программа для работы с ЭП ","show":true},{"name":"1 200 исходящих документов","services":"Электронный документооборот с партнёрами ","show":true},{"name":"5 лицензий Базовая С","services":"Проверка контрагентов ","show":true},{"name":"Актуальные формы отчетов","services":"Готовые формы ","show":true}],"additional_payment":["СМС-уведомления ","Выезд, настройка и обучение ","Дополнительное рабочее место для кадровика"],"advantages":["Безлимитная замена электронной подписи","Проверка на ошибки","Умный календарь бухгалтера","Обучение и семинары с экспертами ФНС","Такском-Информер","Работа с электронными больничными","Отправка новой формы СЗВ-ТД","Сверка по НДС","Актуальные формы отчетов","Техподдержка 24/7"],"classForView":"best stock stock25 tariff","view":false},{"id":16,"name":"Многопользовательское решение","price":"30000","link":"https://order.taxcom.ru/multiorder?RegType=EDO_VashInteres","description":[{"name":"Доклайнер","services":"Программа/сервис  ","show":true},{"name":"ФНС, ПФР, ФСС, Росстат, ЦБ РФ, РПН","services":"Многопользовательский сервис для сдачи отчётности в госорганы:  ","show":true},{"name":"Для компаний с повышенными требованиями к безопасности","services":" Вся информация хранится на вашем сервере или ПК ","show":true},{"name":"Для средних и крупных компаний, уполномоченных представителей","services":" Высокая скорость передачи больших объемов информации Расширенная настройка прав пользователей с мониторингом их действий","show":true}],"classForView":"postpay tariff","view":false},{"id":17,"name":"Удобный. Бюджет","subtitle":"Минимальный старт","price":"3600","link":"https://order.taxcom.ru/multiorder?RegType=EDO_UdobniyBudjet2020","description":[{"name":"Онлайн-спринтер","services":"Программа/сервис ","show":true},{"name":"ФНС, ПФР","services":"Безлимитная отчетность во все подразделения ","show":true},{"name":"В тарифе + бесплатная замена","services":"Электронная подпись (ЭП) ","show":true},{"name":"Лицензия КриптоПро CSP на 1 год","services":"Программа для работы с ЭП ","show":true}],"additional_payment":["СМС-уведомления ","Выезд, настройка и обучение ","Отчетность в ФСС, Росстат, РПН, ЦБ РФ"],"advantages":["Проверка на ошибки","Сверка с ФНС и ПФР","Умный календарь бухгалтера","Обучение и семинары с экспертами ФНС","Такском-Информер","Работа с электронными больничными","Отправка новой формы СЗВ-ТД","Сверка по НДС","Техподдержка 24/7"],"classForView":"stock stock25 tariff","view":false},{"id":18,"name":"Комфортный. Бюджет","subtitle":"Стандартное решение","price":"4200","link":"https://order.taxcom.ru/multiorder?RegType=EDO_ComfortniyBudjet2020","description":[{"name":"Онлайн-спринтер","services":"Программа/сервис ","show":true},{"name":"ФНС, ПФР, ФСС","services":"Безлимитная отчетность во все подразделения ","show":true},{"name":"В тарифе + бесплатная замена","services":"Электронная подпись (ЭП) ","show":true},{"name":"Лицензия КриптоПро CSP на 1 год","services":"Программа для работы с ЭП ","show":true},{"name":"600 исходящих документов","services":"Электронный документооборот с партнёрами ","show":true},{"name":"1 лицензия Базовая С","services":"Проверка контрагентов ","show":true}],"additional_payment":["СМС-уведомления ","Выезд, настройка и обучение ","Отчетность в Росстат, РПН, ЦБ РФ ","Дополнительное рабочее место для кадровика"],"advantages":["Безлимитная замена электронной подписи","Проверка на ошибки","Умный календарь бухгалтера","Обучение и семинары с экспертами ФНС","Такском-Информер","Работа с электронными больничными","Отправка новой формы СЗВ-ТД","Сверка по НДС","Актуальные формы отчетов","Техподдержка 24/7"],"classForView":"stock stock25 tariff","view":false},{"id":19,"name":"Солидный. Бюджет","subtitle":"Полноценная работа для всех","price":"7800","link":"https://order.taxcom.ru/multiorder?RegType=EDO_SolidniyBudjet2020","description":[{"name":"Онлайн-спринтер","services":"Программа/сервис ","show":true},{"name":"ФНС, ПФР, ФСС, Росстат, ЦБ РФ, РПН","services":"Безлимитная отчетность во все подразделения ","show":true},{"name":"В тарифе + бесплатная замена","services":"Электронная подпись (ЭП) ","show":true},{"name":"Лицензия КриптоПро CSP на 1 год","services":"Программа для работы с ЭП ","show":true},{"name":"1 200 исходящих документов","services":"Электронный документооборот с партнёрами ","show":true},{"name":"5 лицензий Базовая С","services":"Проверка контрагентов ","show":true}],"additional_payment":["СМС-уведомления ","Выезд, настройка и обучение ","Дополнительное рабочее место для кадровика"],"advantages":["Безлимитная замена электронной подписи","Проверка на ошибки","Умный календарь бухгалтера","Обучение и семинары с экспертами ФНС","Такском-Информер","Работа с электронными больничными","Отправка новой формы СЗВ-ТД","Сверка по НДС","Актуальные формы отчетов","Техподдержка 24/7"],"classForView":"best stock stock25 tariff","view":false},{"id":20,"name":"Ваш налоговый представитель++","price":"Постоплата","link":"","description":[{"name":"Доклайнер","services":"Программа/сервис  ","show":true},{"name":"ФНС","services":"Безлимитная отчетность во все подразделения  ","show":true},{"name":"В тарифе + бесплатная замена","services":"Электронная подпись (ЭП)  ","show":true},{"name":"Лицензия КриптоПро CSP на 1 год","services":"Программа для работы с ЭП  ","show":true},{"name":"Мобильное приложение Такском-Информер","services":"Получение уведомлений от госорганов ","show":true}],"additional_payment":["ПериодичностьПоквартальная оплата ","Условия расчетаКоличество организаций на обслуживании"],"classForView":"postpay tariff","view":false},{"id":21,"name":"НП++ Онлайн","price":"Постоплата","link":"","description":[{"name":"Онлайн-спринтер","services":"Программа/сервис  ","show":true},{"name":"ФНС, ПФР, ФСС, Росстат, РПН, ЦБ РФ","services":"Безлимитная отчетность во все подразделения  ","show":true},{"name":"В тарифе + бесплатная замена","services":"Электронная подпись (ЭП)  ","show":true},{"name":"Лицензия КриптоПро CSP на 1 год","services":"Программа для работы с ЭП  ","show":true},{"name":"Мобильное приложение Такском-Информер","services":"Получение уведомлений от госорганов ","show":true}],"additional_payment":["ПериодичностьПоквартальная оплата ","Условия расчетаКоличество организаций на обслуживании"],"classForView":"postpay tariff","view":false},{"id":22,"name":"Ваш налоговый представитель НПР","price":"Постоплата","link":"","description":[{"name":"Доклайнер","services":"Программа/сервис  ","show":true},{"name":"ФНС, ПФР, ФСС, Росстат","services":"Безлимитная отчетность во все подразделения  ","show":true},{"name":"В тарифе + бесплатная замена","services":"Электронная подпись (ЭП)  ","show":true},{"name":"Лицензия КриптоПро CSP на 1 год","services":"Программа для работы с ЭП  ","show":true},{"name":"Мобильное приложение Такском-Информер","services":"Получение уведомлений от госорганов ","show":true}],"additional_payment":["ПериодичностьПомесячная оплата ","Условия расчетаКоличество подключенных подразделений госорганов и отправленных документов"],"classForView":"postpay tariff","view":false},{"id":23,"name":"Ваш бухгалтер","price":"Постоплата","link":"","description":[{"name":"Доклайнер","services":"Программа/сервис  ","show":true},{"name":"ФНС, ПФР, ФСС, Росстат","services":"Безлимитная отчетность во все подразделения  ","show":true},{"name":"В тарифе + бесплатная замена","services":"Электронная подпись (ЭП)  ","show":true},{"name":"Лицензия КриптоПро CSP на 1 год","services":"Программа для работы с ЭП  ","show":true},{"name":"Мобильное приложение Такском-Информер","services":"Получение уведомлений от госорганов ","show":true}],"additional_payment":["ПериодичностьПоквартальная оплата ","Условия расчетаКоличество отправленных документов"],"classForView":"postpay tariff","view":false},{"id":24,"name":"НПР Универсальный","price":"Постоплата","link":"","description":[{"name":"На выбор: Доклайнер или Онлайн-спринтер","services":"Программа/сервис  ","show":true},{"name":"ФНС, ПФР, ФСС, Росстат","services":"Безлимитная отчетность во все подразделения  ","show":true},{"name":"В тарифе + бесплатная замена","services":"Электронная подпись (ЭП)  ","show":true},{"name":"Лицензия КриптоПро CSP на 1 год","services":"Программа для работы с ЭП  ","show":true},{"name":"Мобильное приложение Такском-Информер","services":"Получение уведомлений от госорганов ","show":true}],"additional_payment":["ПериодичностьПоквартальная оплата ","Условия расчетаКоличество отправленных документов"],"classForView":"postpay tariff","view":false},{"id":25,"name":"Группа компаний (юридические лица)","price":"4900","classForView":"gp2 tariff tariff-gp","view":false},{"id":26,"name":"Группа компаний (ИП)","price":"1800","classForView":"gp2 tariff tariff-gp","view":false},{"id":27,"name":"Ваша скидка при подключении двух и более организаций","classForView":"tariff tariff-gp","view":false},{"id":28,"name":"Ваша скидка при подключении двух и более организаций","price":"Индивидуальный расчет","classForView":"tariff tariff-gp","view":false},{"id":29,"name":"Комплексный","price":"Авансовыйплатёж","link":"","description":[{"name":"Онлайн-спринтер","services":"Программа/сервис  ","show":true},{"name":"ФНС, ПФР, ФСС, Росстат, РПН, ЦБ РФ","services":"Отчетность во все подразделения  ","show":true},{"name":"В тарифе + бесплатная замена","services":"Электронная подпись (ЭП)  ","show":true},{"name":"Лицензия КриптоПро CSP на 1 год","services":"Программа для работы с ЭП  ","show":true},{"name":"Безлимитная отправка","services":"Пакет отправок отчетов  ","show":true},{"name":"Мобильное приложение Такском-Информер","services":"Получение уведомлений от госорганов  ","show":true},{"name":"100 исходящих документов","services":"Электронный документооборот с партнёрами  ","show":true},{"name":"1 лицензия «Базовая С»","services":"Проверка контрагентов – сервис «Такском-Досье» ","show":true}],"additional_payment":["ПериодичностьГодовой период с авансовой формой расчётов ","Условия расчетаКоличество организаций на обслуживании + пакеты отправок"],"classForView":"newIcon postpay tariff","view":false}]},{"id":2,"name":"Электронная подпись","link":"/centr/all/","img":"https://taxcom.ru/products/img/icon_uc.svg","img_path":"/images/icon_uc.svg","services":[{"id":1,"name":"Электронные торги. Универсальный","description":"Электронная подпись для работы на большинстве популярных торговых площадках, включая «Фабрикант», «B2B-Center» и сервисы госорганов","price":"7500","fast_price":"9500","link":"https://order.taxcom.ru/UC?regtype=ELTORGIU","link_fast":"https://order.taxcom.ru/UC?regtype=ELTORGIUF","view":true},{"id":2,"name":"Электронные торги. Базовый","description":"Электронная подпись для работы на торговых площадках и в сервисах госорганов, не имеющих индивидуальных требований","price":"3500","fast_price":"5500","link":"https://order.taxcom.ru/UC?regtype=ELTBAZA","link_fast":"https://order.taxcom.ru/UC?regtype=ELTBAZAF","view":true},{"id":3,"name":"Электронные торги. B2B-Center","description":"Электронная подпись для площадки «B2B-Center» и взаимодействия с госорганами. Площадка «Фабрикант» не входит","price":"6000","fast_price":"8000","link":"https://order.taxcom.ru/UC?regtype=ELTBAZAB2BC","link_fast":"https://order.taxcom.ru/UC?regtype=ELTBAZAB2BCF","view":true},{"id":4,"name":"Национальное достояние","description":"Электронная подпись для участия в электронных торгах нефтяной и газовой отрасли + все возможности тарифа «Электронные торги»","price":"10000","fast_price":"12000","link":"https://order.taxcom.ru/UC?regtype=NATION","link_fast":"https://order.taxcom.ru/UC?regtype=NATIONF","view":true},{"id":5,"name":"Электронные торги. Фабрикант","description":"Электронная подпись для работы на площадке «Фабрикант» и взаимодействия с госорганами. Площадка «B2B-Center» не входит","price":"6000","fast_price":"8000","link":"https://order.taxcom.ru/UC?regtype=ELTBAZAFABR","link_fast":"https://order.taxcom.ru/UC?regtype=ELTBAZAFABRF","view":true},{"id":6,"name":"Биржа СПбМТСБ","description":"Электронная подпись для работы в системах биржи «СПбМТСБ»","price":"4000","fast_price":"6000","link":"https://order.taxcom.ru/UC?regtype=BIRZHASP","link_fast":"https://order.taxcom.ru/UC?regtype=BIRZHASPF","view":true},{"id":7,"name":"Физическим лицам + КриптоПро CSP","description":"Электронная подпись для оформления сделок с недвижимостью, подачи документов в суд, получения госуслуг в электронном виде, для участия в торгах на ЭТП по реализации имущества банкротов. Со встроенной лицензией КриптоПро CSP","price":"1500","fast_price":"3500","link":"https://order.taxcom.ru/UC?regtype=QSERTFLCSP","link_fast":"https://order.taxcom.ru/UC?regtype=QSERTFLCSPF","view":true},{"id":8,"name":"Ключ директора","description":"Электронная подпись для взаимодействия с государственными органами, а также участия в торгах на ЭТП по реализации имущества","price":"5000","fast_price":"7000","link":"https://order.taxcom.ru/UC?regtype=FEDCERT","link_fast":"https://order.taxcom.ru/UC?regtype=FEDCERTF","view":true},{"id":9,"name":"Электронные госуслуги","description":"Квалифицированная электронная подпись для работы на государственных и муниципальных веб-порталах, для заказа сотрудникам пропусков на перемещение. Выдается на первое лицо организации","price":"1000","fast_price":"3000","link":"https://order.taxcom.ru/UC?regtype=ELGOSUSL&certbyfp=y","link_fast":"https://order.taxcom.ru/UC?regtype=ELGOSUSLF","view":true},{"id":10,"name":"Ключ для отчетности","description":"Дополнительная электронная подпись для сдачи отчетности через интернет в государственные органы: ИФНС, ПФР, ФСС, Росстат, РПН, ЦБ РФ, ФСРАР, ФТС и др.","price":"1250","fast_price":"3250","link":"https://order.taxcom.ru/UC?regtype=QCGKO","link_fast":"https://order.taxcom.ru/UC?regtype=QCGKOF","view":true},{"id":11,"name":"Ключ для отчетности + КриптоПро CSP","description":"Дополнительная электронная подпись для сдачи отчетности через интернет в государственные органы: ИФНС, ПФР, ФСС, Росстат, РПН, ЦБ РФ, ФСРАР, ФТС и др. Со встроенной лицензией КриптоПро CSP","price":"1500","fast_price":"3500","link":"https://order.taxcom.ru/UC?regtype=QCGKOCSP","link_fast":"https://order.taxcom.ru/UC?regtype=QCGKOCSPF","view":true},{"id":12,"name":"ГИИС ДМДК","description":"Электронная подпись для работы в Государственной интегрированной информационной системе в сфере контроля за оборотом драгоценных металлов и драгоценных камней, и изделий из них на всех этапах этого оборота (ГИИС ДМДК)","price":"2000","fast_price":"4000","link":"https://order.taxcom.ru/UC?regtype=GIISDMDK","link_fast":"https://order.taxcom.ru/UC?regtype=GIISDMDKF","view":true},{"id":13,"name":"Ключ для кассы","description":"Электронная подпись для регистрации онлайн-кассы в ФНС и работы в Такском-Кассе. Со встроенной лицензией КриптоПро CSP","price":"1500","fast_price":"3500","link":"https://order.taxcom.ru/UC?regtype=QCOFD","link_fast":"https://order.taxcom.ru/UC?regtype=QCOFDF","view":true},{"id":14,"name":"Ключ для техосмотра","description":"Электронная подпись для работы в Единой автоматизированной информационной системе технического осмотра (ЕАИСТО). Со встроенной лицензией КриптоПро CSP","price":"2000","fast_price":"4000","link":"https://order.taxcom.ru/UC?regtype=PERF","link_fast":"https://order.taxcom.ru/UC?regtype=PERFF","view":true},{"id":15,"name":"Электронные торги. Казахстан","description":"Электронная подпись для работы в системах площадки «ЕТС-Тендер»","price":"3500","fast_price":"5500","link":"https://order.taxcom.ru/UC?regtype=ELTBAZA&utm_referrer=kaz","link_fast":"https://order.taxcom.ru/UC?regtype=ELTBAZAF&utm_referrer=kaz","view":true},{"id":16,"name":"Ключ директора. Базовый","description":"Электронная подпись для работы с гос. органами и на ЭТП по реализации имущества. Ограниченный функционал применения по сравнению с тарифом «Ключ директора»","price":"3000","fast_price":"5000","link":"https://order.taxcom.ru/UC?regtype=FEDCERTBAZA","link_fast":"https://order.taxcom.ru/UC?regtype=FEDCERTBAZAF","view":true},{"id":17,"name":"Физическим лицам","description":"Электронная подпись для оформления сделок с недвижимостью, подачи документов в суд, получения госуслуг в электронном виде, для участия в торгах на ЭТП по реализации имущества банкротов. Выдаётся на 1 год. Выпуск — за сутки или за час","price":"1000","fast_price":"3000","link":"https://order.taxcom.ru/UC?regtype=QSERTFL","link_fast":"https://order.taxcom.ru/UC?regtype=QSERTFLF","view":true},{"id":18,"name":"Ключ для кассы. Базовый","description":"Электронная подпись для регистрации онлайн-кассы в ФНС и работы в Такском-Кассе","price":"1250","fast_price":"3250","link":"https://order.taxcom.ru/UC?regtype=QCOFDBAZA","link_fast":"https://order.taxcom.ru/UC?regtype=QCOFDBAZAF","view":true},{"id":19,"name":"Электронные торги. ТендерСтандарт","description":"Электронная подпись для работы на площадке «ТендерСтандарт» и взаимодействия с госорганами","price":"8500","fast_price":"10500","link":"https://order.taxcom.ru/UC?regtype=ELTTS","link_fast":"https://order.taxcom.ru/UC?regtype=ELTTSF","view":true},{"id":20,"name":"ЕГАИС","description":"Электронная подпись для подключения к ЕГАИС ФСРАР (Росалкогольрегулирование) + защищенный USB-носитель","price":"3700","fast_price":"5700","link":"https://order.taxcom.ru/UC?regtype=EGAIS&certbyfp=y","link_fast":"https://order.taxcom.ru/UC?regtype=EGAISF","view":true},{"id":21,"name":"Физическим лицам. Экспресс","description":"Электронная подпись для оформления сделок с недвижимостью, подачи документов в суд, получения госуслуг в электронном виде, для участия в торгах на ЭТП по реализации имущества банкротов. Выдается на 3 месяца. Выпуск — за сутки или за час","price":"300","fast_price":"2300","link":"https://order.taxcom.ru/UC?RegType=QSERTFLEXS","link_fast":"https://order.taxcom.ru/UC?RegType=QSERTFLEXSF","view":true},{"id":22,"name":"Электронные торги. Эксперт","description":"Электронная подпись для работы на площадке «Эксперт» и взаимодействия с госорганами","price":"8500","fast_price":"10500","link":"https://order.taxcom.ru/UC?regtype=ELTEXP","link_fast":"https://order.taxcom.ru/UC?regtype=ELTEXPF","view":true},{"id":23,"name":"Профессионал","description":"Электронная подпись для взаимодействия с государственными органами, а также участия в торгах на ЭТП по реализации имущества. Выдается на уполномоченное лицо","price":"5000","fast_price":"7000","link":"https://order.taxcom.ru/UC?RegType=PROF","link_fast":"https://order.taxcom.ru/UC?RegType=PROFF","view":true},{"id":24,"name":"Электронные госуслуги. 1 год","description":"Для регистрации на портале «Госуслуги». Выдаётся на 1 год, только на физическое лицо","price":"1000","fast_price":"3000","link":"https://order.taxcom.ru/UC/?RegType=QSERTFL","link_fast":"https://order.taxcom.ru/UC/?RegType=QSERTFLF","view":true},{"id":25,"name":"Электронный ПТС","description":"Электронная подпись для использования в АИС «Система электронных паспортов транспортных средств»","price":"2000","fast_price":"4000","link":"https://order.taxcom.ru/UC?regtype=PTS&certbyfp=y","link_fast":"https://order.taxcom.ru/UC?regtype=PTSF","view":true},{"id":26,"name":"Электронные торги. Южная коммерческая система","description":"Электронная подпись для работы на площадке «Южная коммерческая система» и взаимодействия с госорганами","price":"8500","fast_price":"10500","link":"https://order.taxcom.ru/UC?regtype=ELTUCS","link_fast":"https://order.taxcom.ru/UC?regtype=ELTUCSF","view":true},{"id":27,"name":"Ключ для маркировки","description":"Электронная подпись для регистрации в системе маркировки «Честный ЗНАК» и регистрации онлайн-кассы в ФНС. Со встроенной лицензией КриптоПро CSP","price":"1500","fast_price":"3500","link":"https://order.taxcom.ru/UC?regtype=MARKIROVKA","link_fast":"https://order.taxcom.ru/UC?regtype=MARKIROVKAF","view":true},{"id":28,"name":"Росреестр. Лайт","description":"Электронная подпись для взаимодействия с Федеральной службой государственной регистрации, кадастра и картографии rosreestr.ru. Выдается на 3 месяца, только на физическое лицо","price":"350","fast_price":"2350","link":"https://order.taxcom.ru/UC?RegType=QRUSRLITE","link_fast":"https://order.taxcom.ru/UC?RegType=QRUSRLITEF","view":true},{"id":29,"name":"Ключ для маркировки 2.0","description":"Электронная подпись для работы с устройствами и системами разработчиков кассового оборудования, работы в системах маркировки товаров. Работает только с защищенным USB-носителем Рутокен ЭЦП 2.0","price":"2000","fast_price":"4000","link":"https://order.taxcom.ru/UC?regtype=MARKIROVKA2","link_fast":"https://order.taxcom.ru/UC?regtype=MARKIROVKA2F","view":true},{"id":30,"name":"Зелёный коридор (ФТС)","description":"Электронная подпись для взаимодействия с Федеральной таможенной службой","price":"2000","fast_price":"4000","link":"https://order.taxcom.ru/UC?regtype=FCS","link_fast":"https://order.taxcom.ru/UC?regtype=FCSF","view":true},{"id":31,"name":"Росреестр. ФЛ","description":"Электронная подпись для взаимодействия с Федеральной службой государственной регистрации, кадастра и картографии rosreestr.ru. Выдается на 1 год, только на физическое лицо","price":"1500","fast_price":"3500","link":"https://order.taxcom.ru/UC?regtype=QRUSRLITEG","link_fast":"https://order.taxcom.ru/UC?regtype=QRUSRLITEGF","view":true},{"id":32,"name":"Росреестр","description":"Электронная подпись для взаимодействия с Федеральной службой государственной регистрации, кадастра и картографии rosreestr.ru","price":"3000","fast_price":"5000","link":"https://order.taxcom.ru/UC?regtype=QRUSR&certbyfp=y","link_fast":"https://order.taxcom.ru/UC?regtype=QRUSRF","view":true},{"id":33,"name":"Для подачи документов в вуз/ссуз. 1 год","description":"Для онлайн-подачи документов в учебные заведения и регистрации на портале Госуслуги. Выдаётся на 1 год, только на физическое лицо","price":"1000","fast_price":"3000","link":"https://order.taxcom.ru/UC/?RegType=QSERTFL","link_fast":"https://order.taxcom.ru/UC/?RegType=QSERTFLF","view":true},{"id":34,"name":"Для ПФР","description":"Электронная подпись для использования в системах «Такском-Доклайнз» и других системах","price":"1000","fast_price":"2000","link":"https://order.taxcom.ru/multiorder?regtype=QCEDO","link_fast":"https://order.taxcom.ru/multiorder?regtype=QCEDOF","view":true},{"id":35,"name":"Рособрнадзор","description":"Электронная подпись для использования в системах ФИС ФРДО, ИС ГА, ИС ЛОД и других системах Рособрнадзора","price":"2000","fast_price":"4000","link":"https://order.taxcom.ru/UC?regtype=ROSOBRNADZOR","link_fast":"https://order.taxcom.ru/UC?regtype=ROSOBRNADZORF","view":true},{"id":36,"name":"Для подачи документов в вуз/ссуз. 3 месяца","description":"Для онлайн-подачи документов в учебные заведения и регистрации на портале Госуслуги. Выдаётся на 3 месяца, только на физическое лицо","price":"300","fast_price":"2300","link":"https://order.taxcom.ru/UC?RegType=QSERTFLEXS","link_fast":"https://order.taxcom.ru/UC?RegType=QSERTFLEXSF","view":true},{"id":37,"name":"Для Росфинмониторинга","description":"Электронная подпись для взаимодействия с государственными органами, а также участия в торгах на ЭТП по реализации имущества","price":"5000","fast_price":"7000","link":"https://order.taxcom.ru/multiorder?regtype=FEDCERT","link_fast":"https://order.taxcom.ru/multiorder?regtype=FEDCERTF","view":true},{"id":38,"name":"Для ФНС","description":"Электронная подпись для использования в системах «Такском-Доклайнз» и других системах","price":"1000","fast_price":"3000","link":"https://order.taxcom.ru/multiorder?regtype=QCEDO","link_fast":"https://order.taxcom.ru/multiorder?regtype=QCEDOF","view":true},{"id":39,"name":"Для торгов по банкротству","description":"Электронная подпись для взаимодействия с государственными органами, а также участия в торгах на ЭТП по реализации имущества. Выдается на уполномоченное лицо","price":"5000","fast_price":"7000","link":"https://order.taxcom.ru/multiorder?regtype=PROF","link_fast":"https://order.taxcom.ru/multiorder?regtype=PROFF","view":true},{"id":40,"name":"Для суда","description":"Электронная подпись для оформления сделок с недвижимостью, подачи документов в суд, получения госуслуг в электронном виде, подачи заявления на поступление в вузы и ссузы. Выдаётся на 1 год. Выпуск — за сутки или за час","price":"1000","fast_price":"3000","link":"https://order.taxcom.ru/multiorder?regtype=QSERTFL","link_fast":"https://order.taxcom.ru/multiorder?regtype=QSERTFLF","view":true},{"id":41,"name":"Для госзакупок по 44-ФЗ","description":"Электронная подпись для работы на торговых площадках и в сервисах госорганов, не имеющих индивидуальных требований","price":"3500","fast_price":"5500","link":"https://order.taxcom.ru/multiorder?regtype=ELTBAZA","link_fast":"https://order.taxcom.ru/multiorder?regtype=ELTBAZAF","view":true},{"id":42,"name":"Для маркетплейсов","description":"Электронная подпись для использования в системах «Такском-Доклайнз» и других системах","price":"1500","fast_price":"3500","link":"https://order.taxcom.ru/multiorder?regtype=QCEDOCSP","link_fast":"https://order.taxcom.ru/multiorder?regtype=QCEDOCSPF","view":true},{"id":43,"name":"Ключ для юридических лиц","description":"Электронная подпись для взаимодействия с государственными органами, а также участия в торгах на ЭТП по реализации имущества","price":"3000","fast_price":"5000","link":"https://order.taxcom.ru/UC?regtype=FEDCERTBAZA","link_fast":"https://order.taxcom.ru/UC?regtype=FEDCERTBAZAF","view":true},{"id":44,"name":"Электронные госуслуги. 3 месяца","description":"Электронная подпись для оформления сделок с недвижимостью, подачи документов в суд, получения госуслуг в электронном виде, подачи заявления на поступление в вузы и ссузы и т.д. Выдается на 3 месяца. Выпуск — за сутки или за час","price":"300","fast_price":"2300","link":"https://order.taxcom.ru/multiorder?regtype=QSERTFLEXS","link_fast":"https://order.taxcom.ru/multiorder?regtype=QSERTFLEXSF","view":true},{"id":45,"name":"Электронные госуслуги. 1 год","description":"Электронная подпись для оформления сделок с недвижимостью, подачи документов в суд, получения госуслуг в электронном виде, подачи заявления на поступление в вузы и ссузы. Выдаётся на 1 год. Выпуск — за сутки или за час","price":"1000","fast_price":"3000","link":"https://order.taxcom.ru/multiorder?regtype=QSERTFL","link_fast":"https://order.taxcom.ru/multiorder?regtype=QSERTFLF","view":true},{"id":46,"name":"Для подачи документов в вуз/ссуз. 3 месяца","description":"Электронная подпись для оформления сделок с недвижимостью, подачи документов в суд, получения госуслуг в электронном виде, подачи заявления на поступление в вузы и ссузы и т.д. Выдается на 3 месяца. Выпуск — за сутки или за час","price":"300","fast_price":"2300","link":"https://order.taxcom.ru/multiorder?regtype=QSERTFLEXS","link_fast":"https://order.taxcom.ru/multiorder?regtype=QSERTFLEXSF","view":true},{"id":47,"name":"СКАЛА-ЕПГУ","description":"Электронная подпись для работы в системе «СКАЛА-ЕПГУ». Со встроенной лицензией КриптоПро CSP","price":"2500","fast_price":"4500","link":"https://order.taxcom.ru/UC?regtype=QSCAR","link_fast":"https://order.taxcom.ru/UC?regtype=QSCARF","view":true},{"id":48,"name":"R2D2","description":"Электронная подпись для использования в системах (АИС), для подключения к СМЭВ. Выдается на юр. лицо без указания ФИО, № СНИЛС и должности физ. лица, действующего от имени юр. лица — владельца ЭП","price":"2800","fast_price":"4800","link":"https://order.taxcom.ru/UC?regtype=AISCERT","link_fast":"https://order.taxcom.ru/UC?regtype=AISCERTF","view":true},{"id":49,"name":"Для подачи документов в вуз/ссуз. 1 год","description":"Электронная подпись для оформления сделок с недвижимостью, подачи документов в суд, получения госуслуг в электронном виде, подачи заявления на поступление в вузы и ссузы. Выдаётся на 1 год. Выпуск — за сутки или за час","price":"1000","fast_price":"3000","link":"https://order.taxcom.ru/multiorder?regtype=QSERTFL","link_fast":"https://order.taxcom.ru/multiorder?regtype=QSERTFLF","view":true},{"id":50,"name":"ЛесЕГАИС","description":"Электронная подпись для работы в системе «ЕГАИС учета древесины и сделок с ней»","price":"2000","fast_price":"4000","link":"https://order.taxcom.ru/UC?regtype=LESEGAIS","link_fast":"https://order.taxcom.ru/UC?regtype=LESEGAISF","view":true},{"id":51,"name":"Для корпоративных систем ЭДО","description":"Электронная подпись для использования в системах «Такском-Доклайнз» и других системах","price":"1000","fast_price":"3000","link":"https://order.taxcom.ru/multiorder?regtype=QCEDO","link_fast":"https://order.taxcom.ru/UC?regtype=QCEDOF","view":true},{"id":52,"name":"Для корпоративных систем ЭДО + КриптоПро CSP","description":"Электронная подпись для использования в системах «Такском-Доклайнз» и других системах. Со встроенной лицензией КриптоПро CSP","price":"1500","fast_price":"3500","link":"https://order.taxcom.ru/UC?regtype=QCEDOCSP","link_fast":"https://order.taxcom.ru/UC?regtype=QCEDOCSPF","view":true},{"id":53,"name":"Для маркетплейсов","description":"Электронная подпись для работы в системах маркетплейсов (Wildberries, Ozon, Яндекс.Маркет и др.) Со встроенной лицензией КриптоПро CSP","price":"1500","fast_price":"3500","link":"https://order.taxcom.ru/UC?regtype=QCEDOCSP","link_fast":"https://order.taxcom.ru/UC?regtype=QCEDOCSPF","view":true},{"id":54,"name":"Депозитарный","description":"Электронная подпись для работы в системах ЭДО депозитариев, агентств по раскрытию информации, Федресурса. Со встроенной лицензией КриптоПро CSP","price":"2000","fast_price":"4000","link":"https://order.taxcom.ru/UC?regtype=NRDEPOZIT","link_fast":"https://order.taxcom.ru/UC?regtype=NRDEPOZITF","view":true},{"id":55,"name":"Совершенный","description":"Электронная подпись с возможностью использования служб штампа времени и проверки статуса сертификата. Со встроенной лицензией КриптоПро CSP","price":"2000","fast_price":"4000","link":"https://order.taxcom.ru/UC?regtype=PERF","link_fast":"https://order.taxcom.ru/UC?regtype=PERFF","view":true},{"id":56,"name":"КриптоViP","description":"Электронная подпись для информационных систем и ЭДО. Выпускается при помощи СКЗИ «ViPNet CSP»","price":"1500","fast_price":"3500","link":"https://order.taxcom.ru/UC?regtype=CRYPTOVIP","link_fast":"https://order.taxcom.ru/UC?regtype=CRYPTOVIPF","view":true},{"id":57,"name":"Неквалифицированная ЭП","description":"Электронная подпись для использования в корпоративных системах и других видах ЭДО","price":"1000","fast_price":"3000","link":"https://order.taxcom.ru/UC?regtype=NEPECP","link_fast":"https://order.taxcom.ru/UC?regtype=NEPECPF","view":true},{"id":58,"name":"Неквалифицированная ЭП + КриптоПро CSP","description":"Электронная подпись для использования в корпоративных системах и других видах ЭДО. Со встроенной лицензией КриптоПро CSP","price":"1500","fast_price":"3500","link":"https://order.taxcom.ru/UC?regtype=NEPECPCSP","link_fast":"https://order.taxcom.ru/UC?regtype=NEPECPCSPF","view":true}]}]